dev_tools_loader/__init__.py
dev_tools_loader/__main__.py
dev_tools_loader/cli.py
dev_tools_loader/dev_tools_loader.py
dev_tools_loader-0.1.0a2.dist-info/licenses/LICENSE
dev_tools_loader-0.1.0a2.dist-info/METADATA
dev_tools_loader-0.1.0a2.dist-info/WHEEL
dev_tools_loader-0.1.0a2.dist-info/entry_points.txt
dev_tools_loader-0.1.0a2.dist-info/top_level.txt
dev_tools_loader-0.1.0a2.dist-info/RECORD
