Metadata-Version: 2.4
Name: dev_tools_loader
Version: 0.1.0a2
Summary: Development tools loader
License-Expression: MIT
Requires-Python: >=3.6
License-File: LICENSE
Dynamic: license-file
